blendertoolbox/__init__.py
blendertoolbox/blenderInit.py
blendertoolbox/colorMap.py
blendertoolbox/colorObj.py
blendertoolbox/copyArrowToVertex.py
blendertoolbox/copyToVertexSubset.py
blendertoolbox/createArrow.py
blendertoolbox/createVectorFieldMesh.py
blendertoolbox/discreteColor.py
blendertoolbox/drawBoundaryLoop.py
blendertoolbox/drawEdgeSubset.py
blendertoolbox/drawLines.py
blendertoolbox/drawPoints.py
blendertoolbox/drawSphere.py
blendertoolbox/edgeNormals.py
blendertoolbox/genPolylineMesh.py
blendertoolbox/getEdgeWire.py
blendertoolbox/import_scene_from_blend.py
blendertoolbox/initColorNode.py
blendertoolbox/invisibleGround.py
blendertoolbox/loadShader.py
blendertoolbox/lookAt.py
blendertoolbox/readImagePlane.py
blendertoolbox/readMesh.py
blendertoolbox/readNumpyMesh.py
blendertoolbox/readNumpyPoints.py
blendertoolbox/readOBJ.py
blendertoolbox/readPLY.py
blendertoolbox/readSTL.py
blendertoolbox/recalculateNormals.py
blendertoolbox/renderAnimation.py
blendertoolbox/renderImage.py
blendertoolbox/render_mesh_default.py
blendertoolbox/render_point_cloud_default.py
blendertoolbox/selectOBJ.py
blendertoolbox/setCamera.py
blendertoolbox/setCameraPath.py
blendertoolbox/setCamera_from_UI.py
blendertoolbox/setCamera_orthographic.py
blendertoolbox/setLight_ambient.py
blendertoolbox/setLight_sun.py
blendertoolbox/setLight_threePoints.py
blendertoolbox/setMat_VColor.py
blendertoolbox/setMat_VColorAO.py
blendertoolbox/setMat_VColorEdge.py
blendertoolbox/setMat_amber.py
blendertoolbox/setMat_balloon.py
blendertoolbox/setMat_carPaint.py
blendertoolbox/setMat_ceramic.py
blendertoolbox/setMat_chrome.py
blendertoolbox/setMat_crackedCeramic.py
blendertoolbox/setMat_edge.py
blendertoolbox/setMat_edgeWithTexture.py
blendertoolbox/setMat_emission.py
blendertoolbox/setMat_glass.py
blendertoolbox/setMat_honey.py
blendertoolbox/setMat_matcap.py
blendertoolbox/setMat_metal.py
blendertoolbox/setMat_monotone.py
blendertoolbox/setMat_muscle.py
blendertoolbox/setMat_plastic.py
blendertoolbox-0.5.1.dist-info/LICENSE
blendertoolbox-0.5.1.dist-info/METADATA
blendertoolbox-0.5.1.dist-info/WHEEL
blendertoolbox-0.5.1.dist-info/top_level.txt
blendertoolbox-0.5.1.dist-info/RECORD
