Metadata-Version: 2.1
Name: blendertoolbox
Version: 0.5.1
Summary: A example Python package
Home-page: https://github.com/shuds13/pyexample
Author: Stephen Hudson
Author-email: shudson@anl.gov
License: BSD 2-clause
Classifier: Programming Language :: Python :: 3.10
License-File: LICENSE
